keenetic_client/__init__.py
keenetic_client/client.py
keenetic_client/connection.py
keenetic_client/exceptions.py
keenetic_client-1.0.0.dist-info/METADATA
keenetic_client-1.0.0.dist-info/WHEEL
keenetic_client-1.0.0.dist-info/licenses/LICENSE
keenetic_client-1.0.0.dist-info/RECORD
