Metadata-Version: 2.1
Name: keenetic_client
Version: 1.0.0
Summary: Keenetic router client library
Project-URL: Homepage, https://github.com/sergeykalmyk/keenetic_client
Project-URL: Bug Tracker, https://github.com/sergeykalmyk/keenetic_client/issues
Author-email: "Sergey F. Kalmyk" <skfdev@gmail.com>
License-File: LICENSE
Classifier: License :: OSI Approved :: MIT License
Classifier: Operating System :: OS Independent
Classifier: Programming Language :: Python :: 3
Requires-Python: >=3.6
